irisml/tasks/cache_transformers_model_on_azure_blob.py
irisml/tasks/create_transformers_model.py
irisml/tasks/create_transformers_raw_tokenizer.py
irisml/tasks/create_transformers_text_model.py
irisml/tasks/create_transformers_tokenizer.py
irisml/tasks/create_transformers_text_encoder_model/__init__.py
irisml/tasks/create_transformers_text_encoder_model/create_transformers_text_encoder_model.py
irisml/tasks/create_transformers_text_encoder_model/resources/openai_clip_vit_base_patch32.json
irisml_tasks_transformers-0.0.11.dist-info/LICENSE
irisml_tasks_transformers-0.0.11.dist-info/METADATA
irisml_tasks_transformers-0.0.11.dist-info/WHEEL
irisml_tasks_transformers-0.0.11.dist-info/top_level.txt
irisml_tasks_transformers-0.0.11.dist-info/RECORD
