Metadata-Version: 2.1
Name: irisml-tasks-transformers
Version: 0.0.11
Summary: IrisML Tasks for transformers library
License: MIT License
Project-URL: Repository, https://github.com/microsoft/irisml-tasks-transformers
License-File: LICENSE
Requires-Dist: irisml
Requires-Dist: irisml-tasks-training
Requires-Dist: transformers >=4.31.0
